flasktunnel/__init__.py
flasktunnel/auth.py
flasktunnel/cli.py
flasktunnel/client.py
flasktunnel/config.py
flasktunnel/middleware.py
flasktunnel/server.py
flasktunnel/start_local_server.py
flasktunnel/tunnel.py
flasktunnel/utils.py
flasktunnel_client-1.0.4.dist-info/licenses/LICENSE
flasktunnel_client-1.0.4.dist-info/METADATA
flasktunnel_client-1.0.4.dist-info/WHEEL
flasktunnel_client-1.0.4.dist-info/entry_points.txt
flasktunnel_client-1.0.4.dist-info/top_level.txt
flasktunnel_client-1.0.4.dist-info/RECORD
