Metadata-Version: 2.4
Name: flasktunnel-client
Version: 1.0.4
Summary: Client pour créer des tunnels HTTP sécurisés vers vos applications locales
Home-page: https://github.com/Moesthetics-code/flasktunnel-client.git
Author: Mohamed Ndiaye
Author-email: Mohamed Ndiaye <mouhamedndiayegroupeisi@gmail.com>
License: MIT
Project-URL: Homepage, https://flasktunnel.up.railway.app/
Project-URL: Documentation, https://docs.flasktunnel.dev
Project-URL: Repository, https://github.com/Moesthetics-code/flasktunnel-client.git
Project-URL: Bug Tracker, https://github.com/Moesthetics-code/flasktunnel-client/issues
Keywords: tunnel,ngrok,flask,django,development,webhook,localhost,http,https
Classifier: Development Status :: 5 - Production/Stable
Classifier: Intended Audience :: Developers
Classifier: Topic :: Internet :: WWW/HTTP :: HTTP Servers
Classifier: Topic :: Software Development :: Testing
Classifier: Topic :: System :: Networking
Classifier: License :: OSI Approved :: MIT License
Classifier: Programming Language :: Python :: 3
Classifier: Programming Language :: Python :: 3.7
Classifier: Programming Language :: Python :: 3.8
Classifier: Programming Language :: Python :: 3.9
Classifier: Programming Language :: Python :: 3.10
Classifier: Programming Language :: Python :: 3.11
Classifier: Operating System :: OS Independent
Requires-Python: >=3.7
License-File: LICENSE
Requires-Dist: requests>=2.25.0
Requires-Dist: python-socketio[client]>=5.0.0
Requires-Dist: colorama>=0.4.4
Requires-Dist: click>=8.0.0
Requires-Dist: cryptography>=3.4.0
Requires-Dist: websocket-client>=1.0.0
Dynamic: author
Dynamic: home-page
Dynamic: license-file
Dynamic: requires-python
